LICENSE
MANIFEST.in
README.rst
setup.py
awss3browser/__init__.py
awss3browser/admin.py
awss3browser/file_view.py
awss3browser/models.py
awss3browser/tests.py
awss3browser/urls.py
awss3browser/views.py
awss3browser/migrations/__init__.py
awss3browser/static/assets/images/file-icon/copy-icon.png
awss3browser/static/assets/images/file-icon/cut-icon.png
awss3browser/static/assets/images/file-icon/delete-icon.png
awss3browser/static/assets/images/file-icon/details-icon.png
awss3browser/static/assets/images/file-icon/hyperlink-icon.png
awss3browser/static/assets/images/file-icon/new-folde-iconr.png
awss3browser/static/assets/images/file-icon/paste-icon.png
awss3browser/static/assets/images/file-icon/rename-icon.png
awss3browser/static/assets/images/file-icon/upload-icon.png
awss3browser/static/assets/javascripts/kendo/kendo.all.min.js
awss3browser/static/assets/javascripts/kendo/kendo.timezones.min.js
awss3browser/static/assets/stylesheets/kendo/kendo.bootstrap.min.css
awss3browser/static/assets/stylesheets/kendo/kendo.common.min.css
awss3browser/static/assets/stylesheets/kendo/kendo.default.min.css
awss3browser/static/assets/stylesheets/kendo/kendo.default.mobile.min.css
awss3browser/static/assets/stylesheets/kendo/Bootstrap/editor.png
awss3browser/static/assets/stylesheets/kendo/Bootstrap/imagebrowser.png
awss3browser/static/assets/stylesheets/kendo/Bootstrap/indeterminate.gif
awss3browser/static/assets/stylesheets/kendo/Bootstrap/loading-image.gif
awss3browser/static/assets/stylesheets/kendo/Bootstrap/loading.gif
awss3browser/static/assets/stylesheets/kendo/Bootstrap/loading_2x.gif
awss3browser/static/assets/stylesheets/kendo/Bootstrap/markers.png
awss3browser/static/assets/stylesheets/kendo/Bootstrap/markers_2x.png
awss3browser/static/assets/stylesheets/kendo/Bootstrap/slider-h.gif
awss3browser/static/assets/stylesheets/kendo/Bootstrap/slider-v.gif
awss3browser/static/assets/stylesheets/kendo/Bootstrap/sprite.png
awss3filebrowser.egg-info/PKG-INFO
awss3filebrowser.egg-info/SOURCES.txt
awss3filebrowser.egg-info/dependency_links.txt
awss3filebrowser.egg-info/top_level.txt